README.rst
setup.py
ciscomultiosinfocoordinate/__init__.py
ciscomultiosinfocoordinate/ciscomultiosinfocoordinate.py
ciscomultiosinfocoordinate.egg-info/PKG-INFO
ciscomultiosinfocoordinate.egg-info/SOURCES.txt
ciscomultiosinfocoordinate.egg-info/dependency_links.txt
ciscomultiosinfocoordinate.egg-info/requires.txt
ciscomultiosinfocoordinate.egg-info/top_level.txt